{"map": "Alterac Pass", "timestamp": "2025-03-21T17:16:02.283645+00:00", "durationSeconds": 1298.4, "build": 93810, "gameMode": "StormLeague", "randomSeed": 2694735157, "players": [{"name": "St3LyX", "hero": "Valla", "team": 0, "result": "win", "toon": {"region": 2, "realmId": 1, "profileId": 9907291}, "heroLevel": 20, "talentChoices": [1, 3, 2, 2, 1, 3, 3], "stats": {"takedowns": 23, "deaths": 3, "kills": 7, "assists": 16, "xpContribution": 12581, "healing": 0, "siegeDamage": 93213, "structureDamage": 35657, "heroDamage": 70829, "mercCaptures": 5, "selfHealing": 11339, "timeSpentDead": 97, "timeCCdEnemyHeroes": 73, "creepDamage": 34591, "summonDamage": 5499, "damageTaken": 46314, "damageSoaked": 40236, "highestKillStreak": 17, "protectionGiven": 0, "teamfightHealing": 0, "teamfightDamageTaken": 23332, "teamfightHeroDamage": 30844, "hasAward": 1, "timeOnFire": 195, "physicalDamage": 90250, "spellDamage": 119985, "multikill": 3, "minionKills": 36, "regenGlobes": 40, "votesGiven": 1, "kda": 7.67}, "isRoster": false, "isAlt": false}, {"name": "Matias", "hero": "Anub'arak", "team": 0, "result": "win", "toon": {"region": 2, "realmId": 1, "profileId": 10016237}, "heroLevel": 20, "talentChoices": [1, 2, 1, 1, 1, 1, 1], "stats": {"takedowns": 19, "deaths": 3, "kills": 2, "assists": 17, "xpContribution": 11080, "healing": 0, "siegeDamage": 50732, "structureDamage": 13205, "heroDamage": 40237, "mercCaptures": 3, "selfHealing": 39974, "timeSpentDead": 153, "timeCCdEnemyHeroes": 104, "creepDamage": 49478, "summonDamage": 7053, "damageTaken": 79832, "damageSoaked": 66890, "highestKillStreak": 9, "protectionGiven": 0, "teamfightHealing": 0, "teamfightDamageTaken": 51498, "teamfightHeroDamage": 27199, "timeOnFire": 0, "physicalDamage": 44535, "spellDamage": 103554, "multikill": 2, "minionKills": 25, "regenGlobes": 32, "deathsByStructures": 1, "kda": 6.33}, "isRoster": false, "isAlt": false}, {"name": "taşaksever", "hero": "Genji", "team": 0, "result": "win", "toon": {"region": 2, "realmId": 1, "profileId": 13947932}, "heroLevel": 20, "talentChoices": [2, 1, 3, 2, 1, 2, 2], "stats": {"takedowns": 21, "deaths": 4, "kills": 9, "assists": 12, "xpContribution": 10994, "healing": 0, "siegeDamage": 46536, "structureDamage": 17264, "heroDamage": 59329, "mercCaptures": 3, "selfHealing": 16609, "timeSpentDead": 199, "timeCCdEnemyHeroes": 63, "creepDamage": 8647, "summonDamage": 1643, "damageTaken": 69621, "damageSoaked": 56277, "highestKillStreak": 8, "protectionGiven": 0, "teamfightHealing": 0, "teamfightDamageTaken": 39973, "teamfightHeroDamage": 39616, "timeOnFire": 47, "physicalDamage": 47182, "spellDamage": 72738, "multikill": 3, "minionKills": 27, "regenGlobes": 30, "deathsByStructures": 2, "kda": 5.25}, "isRoster": false, "isAlt": false}, {"name": "RIMBA", "hero": "Stukov", "team": 0, "result": "win", "toon": {"region": 2, "realmId": 1, "profileId": 10317153}, "heroLevel": 14, "talentChoices": [2, 2, 2, 1, 2, 1, 4], "stats": {"takedowns": 22, "deaths": 0, "kills": 5, "assists": 17, "xpContribution": 9990, "healing": 97705, "siegeDamage": 44799, "structureDamage": 19172, "heroDamage": 24240, "mercCaptures": 5, "selfHealing": 0, "timeSpentDead": 0, "timeCCdEnemyHeroes": 304, "creepDamage": 35787, "summonDamage": 1675, "damageTaken": 34154, "damageSoaked": 34154, "highestKillStreak": 22, "protectionGiven": 0, "teamfightHealing": 13608, "teamfightDamageTaken": 7988, "teamfightHeroDamage": 8402, "awardMVP": 1, "hasAward": 1, "timeOnFire": 12, "physicalDamage": 71683, "spellDamage": 40144, "multikill": 2, "minionKills": 32, "regenGlobes": 37, "votesReceived": 1, "kda": 22.0}, "isRoster": false, "isAlt": false}, {"name": "GodOfKings", "hero": "The Lost Vikings", "team": 0, "result": "win", "toon": {"region": 2, "realmId": 1, "profileId": 6635961}, "heroLevel": 20, "talentChoices": [4, 2, 2, 2, 2, 1, 4], "stats": {"takedowns": 16, "deaths": 4, "kills": 4, "assists": 12, "xpContribution": 31391, "healing": 0, "siegeDamage": 137840, "structureDamage": 24905, "heroDamage": 38178, "mercCaptures": 4, "selfHealing": 41268, "timeSpentDead": 0, "timeCCdEnemyHeroes": 52, "creepDamage": 44364, "summonDamage": 1274, "damageTaken": 131784, "damageSoaked": 131784, "highestKillStreak": 4, "protectionGiven": 0, "teamfightHealing": 0, "teamfightDamageTaken": 57746, "teamfightHeroDamage": 23251, "hasAward": 1, "timeOnFire": 0, "physicalDamage": 174229, "spellDamage": 58943, "multikill": 2, "minionKills": 114, "regenGlobes": 100, "deathsByMinions": 2, "kda": 4.0}, "isRoster": false, "isAlt": false}, {"name": "davyzor", "hero": "Blaze", "team": 1, "result": "loss", "toon": {"region": 2, "realmId": 1, "profileId": 8945638}, "heroLevel": 11, "talentChoices": [1, 2, 1, 1, 3, 1, 1], "stats": {"takedowns": 10, "deaths": 6, "kills": 2, "assists": 7, "xpContribution": 9683, "healing": 0, "siegeDamage": 90413, "structureDamage": 7669, "heroDamage": 50128, "mercCaptures": 0, "selfHealing": 10351, "timeSpentDead": 273, "timeCCdEnemyHeroes": 271, "creepDamage": 3073, "summonDamage": 15530, "damageTaken": 84517, "damageSoaked": 51666, "highestKillStreak": 5, "protectionGiven": 0, "teamfightHealing": 0, "teamfightDamageTaken": 65192, "teamfightHeroDamage": 37090, "timeOnFire": 0, "physicalDamage": 53597, "spellDamage": 89108, "multikill": 4, "minionKills": 56, "regenGlobes": 21, "pings": 8, "chatMessages": 2, "chatMessagesTeam": 2, "chatGamesClean": 1, "kda": 1.5}, "isRoster": false, "isAlt": false}, {"name": "Yubes", "hero": "Brightwing", "team": 1, "result": "loss", "toon": {"region": 2, "realmId": 1, "profileId": 8945213}, "heroLevel": 20, "talentChoices": [2, 3, 3, 1, 3, 3, 3], "stats": {"takedowns": 9, "deaths": 4, "kills": 1, "assists": 8, "xpContribution": 10048, "healing": 85725, "siegeDamage": 48953, "structureDamage": 4999, "heroDamage": 26043, "mercCaptures": 1, "selfHealing": 0, "timeSpentDead": 182, "timeCCdEnemyHeroes": 137, "creepDamage": 3825, "summonDamage": 3963, "damageTaken": 45788, "damageSoaked": 34934, "highestKillStreak": 7, "protectionGiven": 0, "teamfightHealing": 17996, "teamfightDamageTaken": 21665, "teamfightHeroDamage": 12091, "timeOnFire": 0, "physicalDamage": 42112, "spellDamage": 39846, "multikill": 3, "minionKills": 42, "regenGlobes": 25, "pings": 15, "chatMessages": 8, "chatMessagesTeam": 8, "chatGamesClean": 1, "kda": 2.25}, "isRoster": false, "isAlt": false}, {"name": "Manlius", "hero": "Samuro", "team": 1, "result": "loss", "toon": {"region": 2, "realmId": 1, "profileId": 10603445}, "heroLevel": 1, "talentChoices": [2, 2, 1, 1, 3, 2, 3], "stats": {"takedowns": 6, "deaths": 4, "kills": 3, "assists": 3, "xpContribution": 27327, "healing": 0, "siegeDamage": 175149, "structureDamage": 8419, "heroDamage": 51844, "mercCaptures": 1, "selfHealing": 9363, "timeSpentDead": 185, "timeCCdEnemyHeroes": 29, "creepDamage": 14966, "summonDamage": 3084, "damageTaken": 51853, "damageSoaked": 38512, "highestKillStreak": 9, "protectionGiven": 0, "teamfightHealing": 0, "teamfightDamageTaken": 30677, "teamfightHeroDamage": 33921, "hasAward": 1, "timeOnFire": 168, "physicalDamage": 125039, "spellDamage": 130837, "multikill": 3, "minionKills": 182, "regenGlobes": 75, "pings": 9, "chatMessages": 4, "chatMessagesTeam": 4, "chatGamesClean": 1, "deathsByStructures": 1, "deathsByMonsters": 1, "kda": 1.5}, "isRoster": false, "isAlt": true, "altName": "Manlius", "partySize": 1, "partyMembers": []}, {"name": "Boo", "hero": "Lunara", "team": 1, "result": "loss", "toon": {"region": 2, "realmId": 1, "profileId": 2449385}, "heroLevel": 7, "talentChoices": [1, 3, 3, 2, 2, 4, 3], "stats": {"takedowns": 8, "deaths": 8, "kills": 4, "assists": 3, "xpContribution": 8556, "healing": 0, "siegeDamage": 54608, "structureDamage": 3389, "heroDamage": 72643, "mercCaptures": 1, "selfHealing": 8679, "timeSpentDead": 359, "timeCCdEnemyHeroes": 172, "creepDamage": 9161, "summonDamage": 2568, "damageTaken": 48937, "damageSoaked": 27795, "highestKillStreak": 5, "protectionGiven": 0, "teamfightHealing": 0, "teamfightDamageTaken": 26046, "teamfightHeroDamage": 31384, "hasAward": 1, "timeOnFire": 0, "physicalDamage": 62035, "spellDamage": 84407, "multikill": 3, "minionKills": 23, "regenGlobes": 20, "pings": 6, "kda": 0.88}, "isRoster": false, "isAlt": false}, {"name": "Lisoth", "hero": "Junkrat", "team": 1, "result": "loss", "toon": {"region": 2, "realmId": 1, "profileId": 12920997}, "heroLevel": 20, "talentChoices": [3, 2, 3, 1, 2, 2, 3], "stats": {"takedowns": 5, "deaths": 5, "kills": 0, "assists": 4, "xpContribution": 14223, "healing": 0, "siegeDamage": 122008, "structureDamage": 1470, "heroDamage": 71018, "mercCaptures": 3, "selfHealing": 0, "timeSpentDead": 220, "timeCCdEnemyHeroes": 46, "creepDamage": 45129, "summonDamage": 10647, "damageTaken": 32922, "damageSoaked": 19696, "highestKillStreak": 5, "protectionGiven": 0, "teamfightHealing": 0, "teamfightDamageTaken": 18934, "teamfightHeroDamage": 37747, "timeOnFire": 0, "physicalDamage": 103508, "spellDamage": 140749, "multikill": 2, "minionKills": 103, "regenGlobes": 24, "pings": 5, "chatMessages": 5, "chatMessagesTeam": 5, "chatGamesClean": 1, "kda": 0.8}, "isRoster": false, "isAlt": false}], "firstBloodTeam": 1, "firstToLevel": {"4": 1, "7": 1, "10": 0, "13": 0, "16": 0, "20": 0}, "teamLevels": {"0": 24, "1": 22}, "firstBossTeam": 0, "firstMercTeam": 0, "draft": [{"type": "ban", "hero": "Dehaka", "team": 1}, {"type": "ban", "hero": "Auriel", "team": 0}, {"type": "ban", "hero": "Stitches", "team": 1}, {"type": "ban", "hero": "Rehgar", "team": 0}, {"type": "pick", "hero": "Brightwing", "team": 1}, {"type": "pick", "hero": "Valla", "team": 0}, {"type": "pick", "hero": "Genji", "team": 0}, {"type": "pick", "hero": "Lunara", "team": 1}, {"type": "pick", "hero": "Blaze", "team": 1}, {"type": "ban", "hero": "Garrosh", "team": 0}, {"type": "ban", "hero": "Anduin", "team": 1}, {"type": "pick", "hero": "Anub'arak", "team": 0}, {"type": "pick", "hero": "Stukov", "team": 0}, {"type": "pick", "hero": "Junkrat", "team": 1}, {"type": "pick", "hero": "Samuro", "team": 1}, {"type": "pick", "hero": "The Lost Vikings", "team": 0}], "matchId": "18523482bc3376d48a64f25a4ca5e81a", "replayFile": "2025-03-21 19.16.02 Alterac Pass.StormReplay"}