{"map": "Tomb of the Spider Queen", "timestamp": "2023-09-20T19:12:45.632476+00:00", "durationSeconds": 1515.1, "build": 90670, "gameMode": "StormLeague", "randomSeed": 2018806715, "players": [{"name": "invertebrate", "hero": "Gazlowe", "team": 0, "result": "win", "toon": {"region": 2, "realmId": 1, "profileId": 51092}, "heroLevel": 9, "talentCodes": ["BN17", "SYDF", "GZ05", "ACLO", "met", "met", "met"], "talentChoices": [1, 2, 2, 2, 2, 2, 4], "stats": {"takedowns": 22, "deaths": 0, "kills": 6, "assists": 16, "xpContribution": 23487, "healing": 0, "siegeDamage": 228658, "structureDamage": 22220, "heroDamage": 93437, "mercCaptures": 4, "selfHealing": 39174, "timeSpentDead": 0, "timeCCdEnemyHeroes": 38, "creepDamage": 26892, "summonDamage": 53061, "damageTaken": 102147, "damageSoaked": 102147, "highestKillStreak": 22, "protectionGiven": 0, "teamfightHealing": 0, "teamfightDamageTaken": 42971, "teamfightHeroDamage": 39639, "timeOnFire": 321, "physicalDamage": 42734, "spellDamage": 309977, "multikill": 6, "minionKills": 162, "regenGlobes": 47, "awardMVP": 1, "hasAward": 1, "votesReceived": 2, "votesGiven": 1, "pings": 17, "chatMessages": 3, "chatMessagesTeam": 3, "kda": 22.0}, "isRoster": true, "rosterName": "invertebrate", "partySize": 2, "partyMembers": ["Engine"]}, {"name": "lhY", "hero": "Fenix", "team": 0, "result": "win", "toon": {"region": 2, "realmId": 1, "profileId": 1157874}, "heroLevel": 13, "talentCodes": ["BN17", "SYDF", "FE01", "NoAP", "met", "met", "met"], "talentChoices": [3, 1, 3, 1, 3, 1, 3], "stats": {"takedowns": 27, "deaths": 2, "kills": 9, "assists": 18, "xpContribution": 16362, "healing": 0, "siegeDamage": 152976, "structureDamage": 18946, "heroDamage": 100992, "mercCaptures": 3, "selfHealing": 5859, "timeSpentDead": 130, "timeCCdEnemyHeroes": 287, "creepDamage": 16052, "summonDamage": 50386, "damageTaken": 64563, "damageSoaked": 59152, "highestKillStreak": 17, "protectionGiven": 0, "teamfightHealing": 0, "teamfightDamageTaken": 20182, "teamfightHeroDamage": 39908, "timeOnFire": 179, "physicalDamage": 184094, "spellDamage": 82537, "multikill": 7, "minionKills": 89, "regenGlobes": 47, "pings": 1, "kda": 13.5}, "isRoster": true, "rosterName": "Engine", "partySize": 2, "partyMembers": ["invertebrate"]}, {"name": "Morty", "hero": "Jaina", "team": 0, "result": "win", "toon": {"region": 2, "realmId": 1, "profileId": 13484598}, "heroLevel": 20, "talentCodes": ["BN2e", "SY93", "JA01", "AN01", "met", "met", "met"], "talentChoices": [2, 2, 3, 1, 1, 3, 1], "stats": {"takedowns": 21, "deaths": 2, "kills": 7, "assists": 14, "xpContribution": 19625, "healing": 0, "siegeDamage": 198776, "structureDamage": 25690, "heroDamage": 72004, "mercCaptures": 5, "selfHealing": 0, "timeSpentDead": 130, "timeCCdEnemyHeroes": 3238, "creepDamage": 19680, "summonDamage": 41137, "damageTaken": 49003, "damageSoaked": 42389, "highestKillStreak": 12, "protectionGiven": 0, "teamfightHealing": 0, "teamfightDamageTaken": 20842, "teamfightHeroDamage": 33498, "timeOnFire": 12, "physicalDamage": 21226, "spellDamage": 269773, "multikill": 4, "minionKills": 134, "regenGlobes": 47, "votesGiven": 1, "pings": 8, "chatMessages": 1, "chatMessagesTeam": 1, "kda": 10.5}, "isRoster": false}, {"name": "Суворова", "hero": "Alexstrasza", "team": 0, "result": "win", "toon": {"region": 2, "realmId": 1, "profileId": 8143148}, "heroLevel": 15, "talentCodes": ["BN7c", "Sy99", "AX01", "ZRTU", "met", "met", "met"], "talentChoices": [3, 2, 3, 2, 1, 3, 3], "stats": {"takedowns": 23, "deaths": 3, "kills": 3, "assists": 20, "xpContribution": 10057, "healing": 149029, "siegeDamage": 71928, "structureDamage": 11027, "heroDamage": 47635, "mercCaptures": 2, "selfHealing": 9646, "timeSpentDead": 192, "timeCCdEnemyHeroes": 254, "creepDamage": 2864, "summonDamage": 22194, "damageTaken": 58053, "damageSoaked": 46575, "highestKillStreak": 14, "protectionGiven": 0, "teamfightHealing": 16718, "teamfightDamageTaken": 29351, "teamfightHeroDamage": 25447, "timeOnFire": 0, "physicalDamage": 48843, "spellDamage": 74306, "multikill": 5, "minionKills": 36, "regenGlobes": 43, "hasAward": 1, "kda": 7.67}, "isRoster": false}, {"name": "SerZsombor", "hero": "Diablo", "team": 0, "result": "win", "toon": {"region": 2, "realmId": 1, "profileId": 7377627}, "heroLevel": 20, "talentCodes": ["BN88", "SY74", "DB03", "MUKY", "met", "met", "met"], "talentChoices": [2, 2, 1, 1, 2, 1, 4], "stats": {"takedowns": 26, "deaths": 4, "kills": 2, "assists": 24, "xpContribution": 11860, "healing": 0, "siegeDamage": 87218, "structureDamage": 13897, "heroDamage": 58877, "mercCaptures": 2, "selfHealing": 43593, "timeSpentDead": 80, "timeCCdEnemyHeroes": 72, "creepDamage": 1391, "summonDamage": 35917, "damageTaken": 206132, "damageSoaked": 177854, "highestKillStreak": 12, "protectionGiven": 0, "teamfightHealing": 0, "teamfightDamageTaken": 127304, "teamfightHeroDamage": 43549, "timeOnFire": 0, "physicalDamage": 43917, "spellDamage": 106807, "multikill": 6, "minionKills": 33, "regenGlobes": 43, "hasAward": 1, "votesGiven": 1, "votesReceived": 1, "chatMessages": 2, "chatMessagesTeam": 2, "kda": 6.5}, "isRoster": false}, {"name": "Kambria", "hero": "Auriel", "team": 1, "result": "loss", "toon": {"region": 2, "realmId": 1, "profileId": 9808380}, "heroLevel": 10, "talentCodes": ["BN14", "SYd8", "AE01", "NoAP", "met", "met", "met"], "talentChoices": [2, 1, 2, 1, 1, 3, 1], "stats": {"takedowns": 8, "deaths": 9, "kills": 0, "assists": 8, "xpContribution": 8892, "healing": 98892, "siegeDamage": 64529, "structureDamage": 2511, "heroDamage": 39527, "mercCaptures": 2, "selfHealing": 0, "timeSpentDead": 365, "timeCCdEnemyHeroes": 15, "creepDamage": 4874, "summonDamage": 3298, "damageTaken": 87864, "damageSoaked": 59977, "highestKillStreak": 6, "protectionGiven": 0, "teamfightHealing": 12228, "teamfightDamageTaken": 45356, "teamfightHeroDamage": 23998, "timeOnFire": 0, "physicalDamage": 25210, "spellDamage": 85407, "multikill": 1, "minionKills": 42, "regenGlobes": 44, "kda": 0.89}, "isRoster": false}, {"name": "L1ght", "hero": "Greymane", "team": 1, "result": "loss", "toon": {"region": 2, "realmId": 1, "profileId": 9687763}, "heroLevel": 7, "talentCodes": ["BN41", "SYd5", "GR01", "AREG", "met", "met", "met"], "talentChoices": [2, 2, 2, 2, 3, 2, 2], "stats": {"takedowns": 10, "deaths": 6, "kills": 3, "assists": 7, "xpContribution": 16866, "healing": 0, "siegeDamage": 149783, "structureDamage": 2395, "heroDamage": 125683, "mercCaptures": 3, "selfHealing": 0, "timeSpentDead": 305, "timeCCdEnemyHeroes": 0, "creepDamage": 29869, "summonDamage": 11807, "damageTaken": 77190, "damageSoaked": 51379, "highestKillStreak": 5, "protectionGiven": 0, "teamfightHealing": 0, "teamfightDamageTaken": 46019, "teamfightHeroDamage": 48875, "timeOnFire": 23, "physicalDamage": 114757, "spellDamage": 195678, "multikill": 2, "minionKills": 124, "regenGlobes": 44, "kda": 1.67}, "isRoster": false}, {"name": "小巨魔", "hero": "Xul", "team": 1, "result": "loss", "toon": {"region": 2, "realmId": 1, "profileId": 13789245}, "heroLevel": 13, "talentCodes": ["BN17", "SYDF", "NE01", "NoAP", "met", "met", "met"], "talentChoices": [3, 3, 2, 2, 1, 1, 3], "stats": {"takedowns": 11, "deaths": 2, "kills": 2, "assists": 9, "xpContribution": 25113, "healing": 0, "siegeDamage": 180992, "structureDamage": 3006, "heroDamage": 84619, "mercCaptures": 0, "selfHealing": 18604, "timeSpentDead": 89, "timeCCdEnemyHeroes": 1815, "creepDamage": 308, "summonDamage": 9666, "damageTaken": 70164, "damageSoaked": 61748, "highestKillStreak": 11, "protectionGiven": 0, "teamfightHealing": 0, "teamfightDamageTaken": 34017, "teamfightHeroDamage": 30281, "timeOnFire": 12, "physicalDamage": 89054, "spellDamage": 179512, "multikill": 2, "minionKills": 198, "regenGlobes": 57, "hasAward": 1, "kda": 5.5}, "isRoster": false}, {"name": "Alfre", "hero": "Mei", "team": 1, "result": "loss", "toon": {"region": 2, "realmId": 1, "profileId": 2769012}, "heroLevel": 20, "talentCodes": ["BN35", "SY1v", "MW01", "MEIA", "met", "met", "met"], "talentChoices": [3, 1, 3, 1, 2, 1, 1], "stats": {"takedowns": 5, "deaths": 6, "kills": 1, "assists": 4, "xpContribution": 10678, "healing": 0, "siegeDamage": 95285, "structureDamage": 7759, "heroDamage": 45111, "mercCaptures": 0, "selfHealing": 39612, "timeSpentDead": 280, "timeCCdEnemyHeroes": 775, "creepDamage": 0, "summonDamage": 7891, "damageTaken": 113038, "damageSoaked": 83190, "highestKillStreak": 2, "protectionGiven": 0, "teamfightHealing": 0, "teamfightDamageTaken": 77452, "teamfightHeroDamage": 26147, "timeOnFire": 0, "physicalDamage": 41046, "spellDamage": 104189, "multikill": 1, "minionKills": 57, "regenGlobes": 42, "kda": 0.83}, "isRoster": false}, {"name": "TortueHuppée", "hero": "Nazeebo", "team": 1, "result": "loss", "toon": {"region": 2, "realmId": 1, "profileId": 13399108}, "heroLevel": 20, "talentCodes": ["BN17", "SYDF", "WI01", "NoAP", "met", "met", "met"], "talentChoices": [1, 1, 1, 1, 3, 1, 3], "stats": {"takedowns": 10, "deaths": 4, "kills": 5, "assists": 5, "xpContribution": 18753, "healing": 0, "siegeDamage": 163735, "structureDamage": 12712, "heroDamage": 129162, "mercCaptures": 1, "selfHealing": 21846, "timeSpentDead": 196, "timeCCdEnemyHeroes": 105, "creepDamage": 16365, "summonDamage": 21421, "damageTaken": 68046, "damageSoaked": 51909, "highestKillStreak": 6, "protectionGiven": 0, "teamfightHealing": 0, "teamfightDamageTaken": 33708, "teamfightHeroDamage": 56470, "timeOnFire": 109, "physicalDamage": 46500, "spellDamage": 259710, "multikill": 2, "minionKills": 136, "regenGlobes": 42, "hasAward": 1, "kda": 2.5}, "isRoster": false}], "firstBloodTeam": 0, "matchId": "3a497dbcb06209bcea728091501620a3", "replayFile": "2023-09-20 22.12.45 Tomb of the Spider Queen.StormReplay"}