{"map": "Infernal Shrines", "timestamp": "2025-02-10T19:37:41.484001+00:00", "durationSeconds": 818.2, "build": 93640, "gameMode": "StormLeague", "randomSeed": 893030285, "players": [{"name": "ПоФанУ", "hero": "Nova", "team": 0, "result": "win", "toon": {"region": 2, "realmId": 1, "profileId": 13845849}, "heroLevel": 7, "talentCodes": ["BN17", "SYDF", "NA01", "AWHI", "met", "met", "met"], "talentChoices": [1, 3, 3, 2, 2, 2, 0], "stats": {"takedowns": 13, "deaths": 0, "kills": 5, "assists": 8, "xpContribution": 8205, "healing": 0, "siegeDamage": 25806, "structureDamage": 11943, "heroDamage": 28469, "mercCaptures": 4, "selfHealing": 0, "timeSpentDead": 0, "timeCCdEnemyHeroes": 94, "creepDamage": 6119, "summonDamage": 4058, "damageTaken": 11615, "damageSoaked": 11615, "highestKillStreak": 13, "protectionGiven": 0, "teamfightHealing": 0, "teamfightDamageTaken": 645, "teamfightHeroDamage": 6415, "timeOnFire": 97, "physicalDamage": 37052, "spellDamage": 25476, "multikill": 2, "minionKills": 15, "regenGlobes": 29, "kda": 13.0}, "isRoster": false}, {"name": "Furkan", "hero": "Garrosh", "team": 0, "result": "win", "toon": {"region": 2, "realmId": 1, "profileId": 6882110}, "heroLevel": 18, "talentCodes": ["BN03", "SY0p", "GO02", "AKEL", "met", "met", "met"], "talentChoices": [2, 3, 2, 2, 2, 3, 0], "stats": {"takedowns": 11, "deaths": 1, "kills": 1, "assists": 10, "xpContribution": 6479, "healing": 0, "siegeDamage": 29573, "structureDamage": 5798, "heroDamage": 13335, "mercCaptures": 3, "selfHealing": 4313, "timeSpentDead": 26, "timeCCdEnemyHeroes": 94, "creepDamage": 15448, "summonDamage": 3730, "damageTaken": 34115, "damageSoaked": 30943, "highestKillStreak": 8, "protectionGiven": 0, "teamfightHealing": 0, "teamfightDamageTaken": 13922, "teamfightHeroDamage": 6669, "timeOnFire": 0, "physicalDamage": 26856, "spellDamage": 32075, "multikill": 1, "minionKills": 23, "regenGlobes": 33, "kda": 11.0}, "isRoster": false}, {"name": "キラ", "hero": "Illidan", "team": 0, "result": "win", "toon": {"region": 2, "realmId": 1, "profileId": 12258715}, "heroLevel": 20, "talentCodes": ["BN4d", "Sy93", "IL01", "ALIL", "met", "met", "met"], "talentChoices": [1, 3, 3, 1, 1, 1, 0], "stats": {"takedowns": 11, "deaths": 1, "kills": 3, "assists": 8, "xpContribution": 13966, "healing": 0, "siegeDamage": 145305, "structureDamage": 48185, "heroDamage": 31282, "mercCaptures": 2, "selfHealing": 71382, "timeSpentDead": 20, "timeCCdEnemyHeroes": 10, "creepDamage": 14840, "summonDamage": 15647, "damageTaken": 93186, "damageSoaked": 91003, "highestKillStreak": 11, "protectionGiven": 0, "teamfightHealing": 0, "teamfightDamageTaken": 51060, "teamfightHeroDamage": 21531, "awardMVP": 1, "hasAward": 1, "timeOnFire": 140, "physicalDamage": 74170, "spellDamage": 113724, "multikill": 2, "minionKills": 88, "regenGlobes": 28, "kda": 11.0}, "isRoster": false}, {"name": "BabyGanoush", "hero": "Valla", "team": 0, "result": "win", "toon": {"region": 2, "realmId": 1, "profileId": 12702864}, "heroLevel": 20, "talentCodes": ["BN17", "SY8p", "DH02", "NoAP", "met", "met", "met"], "talentChoices": [3, 2, 3, 2, 3, 3, 0], "stats": {"takedowns": 14, "deaths": 0, "kills": 5, "assists": 9, "xpContribution": 9205, "healing": 0, "siegeDamage": 90499, "structureDamage": 31386, "heroDamage": 30049, "mercCaptures": 6, "selfHealing": 4497, "timeSpentDead": 0, "timeCCdEnemyHeroes": 5, "creepDamage": 45486, "summonDamage": 11797, "damageTaken": 30611, "damageSoaked": 30611, "highestKillStreak": 14, "protectionGiven": 0, "teamfightHealing": 0, "teamfightDamageTaken": 12353, "teamfightHeroDamage": 12456, "hasAward": 1, "timeOnFire": 12, "physicalDamage": 126942, "spellDamage": 33612, "multikill": 2, "minionKills": 51, "regenGlobes": 38, "kda": 14.0}, "isRoster": false}, {"name": "BabyBandit", "hero": "Whitemane", "team": 0, "result": "win", "toon": {"region": 2, "realmId": 1, "profileId": 13899006}, "heroLevel": 20, "talentCodes": ["BN17", "SY3K", "WH02", "BTHR", "met", "met", "met"], "talentChoices": [1, 3, 3, 1, 1, 2, 0], "stats": {"takedowns": 15, "deaths": 0, "kills": 2, "assists": 13, "xpContribution": 4641, "healing": 66198, "siegeDamage": 14837, "structureDamage": 4590, "heroDamage": 15632, "mercCaptures": 2, "selfHealing": 0, "timeSpentDead": 0, "timeCCdEnemyHeroes": 890, "creepDamage": 1951, "summonDamage": 3125, "damageTaken": 24765, "damageSoaked": 24765, "highestKillStreak": 15, "protectionGiven": 0, "teamfightHealing": 12321, "teamfightDamageTaken": 8169, "teamfightHeroDamage": 6527, "hasAward": 1, "timeOnFire": 0, "physicalDamage": 8944, "spellDamage": 20956, "multikill": 2, "minionKills": 8, "regenGlobes": 29, "kda": 15.0}, "isRoster": false}, {"name": "Manlius", "hero": "Zagara", "team": 1, "result": "loss", "toon": {"region": 2, "realmId": 1, "profileId": 10603445}, "heroLevel": 1, "talentCodes": ["BN17", "SYDF", "ZA01", "NoAP", "met", "met", "met"], "talentChoices": [2, 1, 3, 1, 3, 0, 0], "stats": {"takedowns": 2, "deaths": 3, "kills": 0, "assists": 2, "xpContribution": 7047, "healing": 0, "siegeDamage": 42127, "structureDamage": 3253, "heroDamage": 27878, "mercCaptures": 0, "selfHealing": 0, "timeSpentDead": 85, "timeCCdEnemyHeroes": 8, "creepDamage": 8511, "summonDamage": 0, "damageTaken": 21625, "damageSoaked": 14266, "highestKillStreak": 2, "protectionGiven": 0, "teamfightHealing": 0, "teamfightDamageTaken": 9521, "teamfightHeroDamage": 7325, "timeOnFire": 0, "physicalDamage": 15456, "spellDamage": 69077, "multikill": 0, "minionKills": 50, "regenGlobes": 14, "pings": 1, "kda": 0.67}, "isRoster": false}, {"name": "Grezor", "hero": "Johanna", "team": 1, "result": "loss", "toon": {"region": 2, "realmId": 1, "profileId": 885944}, "heroLevel": 20, "talentCodes": ["BN14", "SY62", "CR04", "BR01", "met", "met", "met"], "talentChoices": [1, 1, 1, 2, 3, 0, 0], "stats": {"takedowns": 2, "deaths": 3, "kills": 1, "assists": 1, "xpContribution": 3775, "healing": 3860, "siegeDamage": 24375, "structureDamage": 0, "heroDamage": 14123, "mercCaptures": 0, "selfHealing": 5705, "timeSpentDead": 87, "timeCCdEnemyHeroes": 46, "creepDamage": 4199, "summonDamage": 0, "damageTaken": 35701, "damageSoaked": 23083, "highestKillStreak": 2, "protectionGiven": 0, "teamfightHealing": 0, "teamfightDamageTaken": 29045, "teamfightHeroDamage": 9425, "hasAward": 1, "timeOnFire": 0, "physicalDamage": 6458, "spellDamage": 37800, "multikill": 0, "minionKills": 16, "regenGlobes": 18, "pings": 1, "kda": 0.67}, "isRoster": true, "rosterName": "Grezor", "partySize": 3, "partyMembers": ["Engine", "XeduR"]}, {"name": "lhY", "hero": "Deckard", "team": 1, "result": "loss", "toon": {"region": 2, "realmId": 1, "profileId": 1157874}, "heroLevel": 8, "talentCodes": ["BN17", "SYDF", "DC01", "NoAP", "met", "met", "met"], "talentChoices": [2, 1, 1, 1, 2, 0, 0], "stats": {"takedowns": 2, "deaths": 3, "kills": 0, "assists": 2, "xpContribution": 2260, "healing": 36421, "siegeDamage": 11858, "structureDamage": 220, "heroDamage": 7034, "mercCaptures": 0, "selfHealing": 0, "timeSpentDead": 77, "timeCCdEnemyHeroes": 104, "creepDamage": 3884, "summonDamage": 0, "damageTaken": 18258, "damageSoaked": 10316, "highestKillStreak": 1, "protectionGiven": 5278, "teamfightHealing": 4830, "teamfightDamageTaken": 14281, "teamfightHeroDamage": 3957, "timeOnFire": 0, "physicalDamage": 3804, "spellDamage": 20185, "multikill": 0, "minionKills": 10, "regenGlobes": 10, "chatMessages": 2, "chatMessagesTeam": 2, "kda": 0.67}, "isRoster": true, "rosterName": "Engine", "partySize": 3, "partyMembers": ["Grezor", "XeduR"]}, {"name": "XeduR", "hero": "Falstad", "team": 1, "result": "loss", "toon": {"region": 2, "realmId": 1, "profileId": 8623376}, "heroLevel": 20, "talentCodes": ["BNc5", "SY77", "FA01", "FALS", "met", "met", "met"], "talentChoices": [1, 3, 2, 1, 2, 0, 0], "stats": {"takedowns": 2, "deaths": 5, "kills": 1, "assists": 1, "xpContribution": 2798, "healing": 0, "siegeDamage": 25343, "structureDamage": 0, "heroDamage": 31282, "mercCaptures": 0, "selfHealing": 4101, "timeSpentDead": 132, "timeCCdEnemyHeroes": 90, "creepDamage": 11349, "summonDamage": 0, "damageTaken": 24397, "damageSoaked": 14274, "highestKillStreak": 1, "protectionGiven": 0, "teamfightHealing": 0, "teamfightDamageTaken": 17124, "teamfightHeroDamage": 13020, "timeOnFire": 0, "physicalDamage": 25124, "spellDamage": 49720, "multikill": 0, "minionKills": 19, "regenGlobes": 11, "pings": 1, "kda": 0.4}, "isRoster": true, "rosterName": "XeduR", "partySize": 3, "partyMembers": ["Grezor", "Engine"]}, {"name": "RedPanda", "hero": "Azmodan", "team": 1, "result": "loss", "toon": {"region": 2, "realmId": 1, "profileId": 12664903}, "heroLevel": 11, "talentCodes": ["BN17", "SYDF", "AZ01", "BR01", "met", "met", "met"], "talentChoices": [2, 1, 1, 1, 3, 0, 0], "stats": {"takedowns": 1, "deaths": 2, "kills": 0, "assists": 1, "xpContribution": 9601, "healing": 0, "siegeDamage": 65121, "structureDamage": 2612, "heroDamage": 32074, "mercCaptures": 0, "selfHealing": 0, "timeSpentDead": 37, "timeCCdEnemyHeroes": 0, "creepDamage": 7870, "summonDamage": 0, "damageTaken": 27484, "damageSoaked": 21576, "highestKillStreak": 1, "protectionGiven": 0, "teamfightHealing": 0, "teamfightDamageTaken": 19258, "teamfightHeroDamage": 6626, "hasAward": 1, "timeOnFire": 0, "physicalDamage": 9958, "spellDamage": 96972, "multikill": 0, "minionKills": 81, "regenGlobes": 17, "pings": 1, "kda": 0.5}, "isRoster": false}], "firstBloodTeam": 0, "matchId": "75ffd2937702f9a8b479378fbc4df5c5", "replayFile": "2025-02-10 21.37.41 Infernal Shrines.StormReplay"}