{"map": "Silver City", "timestamp": "2023-08-22T19:01:13.937629+00:00", "durationSeconds": 708.4, "build": 90670, "gameMode": "ARAM", "randomSeed": 3354679609, "players": [{"name": "MrMustache13", "hero": "Valla", "team": 0, "result": "win", "toon": {"region": 2, "realmId": 1, "profileId": 10579670}, "heroLevel": 1, "talentCodes": ["", "", "", "", "met", "met", "met"], "talentChoices": [3, 2, 3, 2, 2, 3, 2], "stats": {"takedowns": 36, "deaths": 1, "kills": 14, "assists": 22, "xpContribution": 9546, "healing": 0, "siegeDamage": 47888, "structureDamage": 29441, "heroDamage": 86125, "mercCaptures": 2, "selfHealing": 12169, "timeSpentDead": 13, "timeCCdEnemyHeroes": 3, "creepDamage": 5149, "summonDamage": 0, "damageTaken": 34392, "damageSoaked": 32485, "highestKillStreak": 25, "protectionGiven": 0, "teamfightHealing": 0, "teamfightDamageTaken": 17256, "teamfightHeroDamage": 58420, "timeOnFire": 36, "physicalDamage": 104490, "spellDamage": 34397, "multikill": 8, "minionKills": 21, "regenGlobes": 27, "hasAward": 1, "kda": 36.0}, "isRoster": false}, {"name": "Sl1p3R", "hero": "Garrosh", "team": 0, "result": "win", "toon": {"region": 2, "realmId": 1, "profileId": 8667720}, "heroLevel": 1, "talentCodes": ["", "", "", "", "met", "met", "met"], "talentChoices": [1, 3, 2, 2, 1, 3, 0], "stats": {"takedowns": 35, "deaths": 1, "kills": 6, "assists": 29, "xpContribution": 9616, "healing": 0, "siegeDamage": 21158, "structureDamage": 11497, "heroDamage": 33172, "mercCaptures": 1, "selfHealing": 10633, "timeSpentDead": 5, "timeCCdEnemyHeroes": 240, "creepDamage": 0, "summonDamage": 0, "damageTaken": 54706, "damageSoaked": 52478, "highestKillStreak": 33, "protectionGiven": 0, "teamfightHealing": 45, "teamfightDamageTaken": 42954, "teamfightHeroDamage": 30204, "timeOnFire": 275, "physicalDamage": 17844, "spellDamage": 36486, "multikill": 8, "minionKills": 19, "regenGlobes": 28, "hasAward": 1, "kda": 35.0}, "isRoster": false}, {"name": "Encestor", "hero": "Brightwing", "team": 0, "result": "win", "toon": {"region": 2, "realmId": 1, "profileId": 10628870}, "heroLevel": 1, "talentCodes": ["", "", "", "", "met", "met", "met"], "talentChoices": [1, 1, 3, 1, 3, 2, 0], "stats": {"takedowns": 35, "deaths": 1, "kills": 3, "assists": 32, "xpContribution": 7762, "healing": 91172, "siegeDamage": 10630, "structureDamage": 5164, "heroDamage": 15635, "mercCaptures": 2, "selfHealing": 0, "timeSpentDead": 13, "timeCCdEnemyHeroes": 0, "creepDamage": 3550, "summonDamage": 0, "damageTaken": 23284, "damageSoaked": 21256, "highestKillStreak": 24, "protectionGiven": 0, "teamfightHealing": 27248, "teamfightDamageTaken": 16724, "teamfightHeroDamage": 10549, "timeOnFire": 0, "physicalDamage": 13564, "spellDamage": 16251, "multikill": 8, "minionKills": 5, "regenGlobes": 29, "hasAward": 1, "kda": 35.0}, "isRoster": false}, {"name": "Boca020", "hero": "Dehaka", "team": 0, "result": "win", "toon": {"region": 2, "realmId": 1, "profileId": 9343562}, "heroLevel": 1, "talentCodes": ["", "", "", "", "met", "met", "met"], "talentChoices": [1, 3, 3, 1, 3, 1, 0], "stats": {"takedowns": 34, "deaths": 2, "kills": 7, "assists": 27, "xpContribution": 9956, "healing": 0, "siegeDamage": 29502, "structureDamage": 12758, "heroDamage": 37647, "mercCaptures": 2, "selfHealing": 25246, "timeSpentDead": 35, "timeCCdEnemyHeroes": 51, "creepDamage": 5086, "summonDamage": 0, "damageTaken": 65275, "damageSoaked": 57907, "highestKillStreak": 18, "protectionGiven": 0, "teamfightHealing": 0, "teamfightDamageTaken": 50965, "teamfightHeroDamage": 33196, "timeOnFire": 0, "physicalDamage": 25616, "spellDamage": 46619, "multikill": 7, "minionKills": 31, "regenGlobes": 28, "kda": 17.0}, "isRoster": false}, {"name": "EAtmYkodO", "hero": "Mephisto", "team": 0, "result": "win", "toon": {"region": 2, "realmId": 1, "profileId": 13302699}, "heroLevel": 1, "talentCodes": ["", "", "", "", "met", "met", "met"], "talentChoices": [3, 3, 2, 2, 3, 2, 3], "stats": {"takedowns": 36, "deaths": 2, "kills": 6, "assists": 30, "xpContribution": 11363, "healing": 0, "siegeDamage": 86007, "structureDamage": 36784, "heroDamage": 98375, "mercCaptures": 0, "selfHealing": 0, "timeSpentDead": 35, "timeCCdEnemyHeroes": 555, "creepDamage": 949, "summonDamage": 0, "damageTaken": 39713, "damageSoaked": 33633, "highestKillStreak": 19, "protectionGiven": 0, "teamfightHealing": 0, "teamfightDamageTaken": 28637, "teamfightHeroDamage": 85840, "timeOnFire": 224, "physicalDamage": 17086, "spellDamage": 167832, "multikill": 8, "minionKills": 41, "regenGlobes": 30, "awardMVP": 1, "hasAward": 1, "kda": 18.0}, "isRoster": false}, {"name": "XeduR", "hero": "Hogger", "team": 1, "result": "loss", "toon": {"region": 2, "realmId": 1, "profileId": 8623376}, "heroLevel": 1, "talentCodes": ["", "", "", "", "met", "met", "met"], "talentChoices": [1, 3, 2, 1, 3, 0, 0], "stats": {"takedowns": 5, "deaths": 6, "kills": 0, "assists": 5, "xpContribution": 6947, "healing": 0, "siegeDamage": 34391, "structureDamage": 6272, "heroDamage": 42955, "mercCaptures": 0, "selfHealing": 23710, "timeSpentDead": 106, "timeCCdEnemyHeroes": 139, "creepDamage": 0, "summonDamage": 0, "damageTaken": 80845, "damageSoaked": 58014, "highestKillStreak": 2, "protectionGiven": 0, "teamfightHealing": 0, "teamfightDamageTaken": 75272, "teamfightHeroDamage": 41274, "timeOnFire": 0, "physicalDamage": 15311, "spellDamage": 61417, "multikill": 1, "minionKills": 27, "regenGlobes": 7, "pings": 1, "deathsByStructures": 1, "kda": 0.83}, "isRoster": true, "rosterName": "XeduR", "partySize": 3, "partyMembers": ["Engine", "invertebrate"]}, {"name": "lhY", "hero": "Arthas", "team": 1, "result": "loss", "toon": {"region": 2, "realmId": 1, "profileId": 1157874}, "heroLevel": 1, "talentCodes": ["", "", "", "", "met", "met", "met"], "talentChoices": [2, 3, 2, 2, 3, 0, 0], "stats": {"takedowns": 7, "deaths": 10, "kills": 1, "assists": 6, "xpContribution": 5536, "healing": 0, "siegeDamage": 17195, "structureDamage": 1833, "heroDamage": 31075, "mercCaptures": 0, "selfHealing": 12675, "timeSpentDead": 179, "timeCCdEnemyHeroes": 324, "creepDamage": 0, "summonDamage": 0, "damageTaken": 85959, "damageSoaked": 42282, "highestKillStreak": 4, "protectionGiven": 0, "teamfightHealing": 0, "teamfightDamageTaken": 83175, "teamfightHeroDamage": 28988, "timeOnFire": 0, "physicalDamage": 19174, "spellDamage": 28449, "multikill": 1, "minionKills": 12, "regenGlobes": 6, "hasAward": 1, "votesReceived": 1, "chatMessages": 2, "chatMessagesTeam": 2, "chatGamesClean": 1, "kda": 0.7}, "isRoster": true, "rosterName": "Engine", "partySize": 3, "partyMembers": ["XeduR", "invertebrate"]}, {"name": "invertebrate", "hero": "Auriel", "team": 1, "result": "loss", "toon": {"region": 2, "realmId": 1, "profileId": 51092}, "heroLevel": 1, "talentCodes": ["", "", "", "", "met", "met", "met"], "talentChoices": [3, 3, 3, 2, 3, 1, 0], "stats": {"takedowns": 6, "deaths": 7, "kills": 1, "assists": 5, "xpContribution": 5136, "healing": 45625, "siegeDamage": 15084, "structureDamage": 1077, "heroDamage": 32949, "mercCaptures": 0, "selfHealing": 0, "timeSpentDead": 128, "timeCCdEnemyHeroes": 27, "creepDamage": 0, "summonDamage": 0, "damageTaken": 40680, "damageSoaked": 22503, "highestKillStreak": 4, "protectionGiven": 0, "teamfightHealing": 18864, "teamfightDamageTaken": 34468, "teamfightHeroDamage": 24838, "timeOnFire": 0, "physicalDamage": 12753, "spellDamage": 34084, "multikill": 1, "minionKills": 9, "regenGlobes": 10, "votesGiven": 1, "chatMessages": 2, "chatMessagesTeam": 2, "pings": 1, "chatGamesClean": 1, "kda": 0.86}, "isRoster": true, "rosterName": "invertebrate", "partySize": 3, "partyMembers": ["XeduR", "Engine"]}, {"name": "Bankai", "hero": "Kael'thas", "team": 1, "result": "loss", "toon": {"region": 2, "realmId": 1, "profileId": 168582}, "heroLevel": 1, "talentCodes": ["", "", "", "", "met", "met", "met"], "talentChoices": [3, 1, 2, 2, 1, 2, 0], "stats": {"takedowns": 7, "deaths": 8, "kills": 3, "assists": 4, "xpContribution": 5126, "healing": 0, "siegeDamage": 17632, "structureDamage": 2770, "heroDamage": 26987, "mercCaptures": 0, "selfHealing": 0, "timeSpentDead": 131, "timeCCdEnemyHeroes": 14, "creepDamage": 0, "summonDamage": 0, "damageTaken": 44525, "damageSoaked": 25743, "highestKillStreak": 4, "protectionGiven": 0, "teamfightHealing": 0, "teamfightDamageTaken": 38612, "teamfightHeroDamage": 21391, "timeOnFire": 0, "physicalDamage": 11235, "spellDamage": 33310, "multikill": 1, "minionKills": 16, "regenGlobes": 7, "kda": 0.88}, "isRoster": false}, {"name": "Stefan", "hero": "Auriel", "team": 1, "result": "loss", "toon": {"region": 2, "realmId": 1, "profileId": 119824}, "heroLevel": 1, "talentCodes": ["", "", "", "", "met", "met", "met"], "talentChoices": [2, 1, 2, 2, 1, 0, 0], "stats": {"takedowns": 7, "deaths": 5, "kills": 2, "assists": 5, "xpContribution": 5243, "healing": 66306, "siegeDamage": 17261, "structureDamage": 1438, "heroDamage": 28426, "mercCaptures": 0, "selfHealing": 0, "timeSpentDead": 100, "timeCCdEnemyHeroes": 20, "creepDamage": 0, "summonDamage": 0, "damageTaken": 39616, "damageSoaked": 25990, "highestKillStreak": 4, "protectionGiven": 0, "teamfightHealing": 32973, "teamfightDamageTaken": 35406, "teamfightHeroDamage": 25452, "timeOnFire": 0, "physicalDamage": 7094, "spellDamage": 38415, "multikill": 1, "minionKills": 16, "regenGlobes": 9, "pings": 4, "chatMessages": 3, "chatMessagesTeam": 3, "chatGamesClean": 1, "kda": 1.4}, "isRoster": false}], "firstBloodTeam": 0, "firstToLevel": {"4": 0, "7": 0, "10": 0, "13": 0, "16": 0, "20": 0}, "firstBossTeam": null, "firstMercTeam": 0, "matchId": "a71f0f48ca96a0d2f84a6a9571be428f", "replayFile": "2023-08-22 22.01.13 Silver City.StormReplay"}